deltabot_web2pdf/__init__.py
deltabot_web2pdf/__main__.py
deltabot_web2pdf/_version.py
deltabot_web2pdf/hooks.py
deltabot_web2pdf-0.2.0.dist-info/LICENSE
deltabot_web2pdf-0.2.0.dist-info/METADATA
deltabot_web2pdf-0.2.0.dist-info/WHEEL
deltabot_web2pdf-0.2.0.dist-info/entry_points.txt
deltabot_web2pdf-0.2.0.dist-info/top_level.txt
deltabot_web2pdf-0.2.0.dist-info/RECORD
