Metadata-Version: 2.1
Name: deltabot-web2pdf
Version: 0.2.0
Summary: Download websites as PDF in Delta Chat
Author-email: adbenitez <adb@merlinux.eu>
Project-URL: Homepage, https://github.com/deltachat-bot/web2pdf
Keywords: deltachat,bot,web,pdf
Classifier: Development Status :: 4 - Beta
Classifier: Programming Language :: Python
Classifier: License :: OSI Approved :: GNU General Public License v3 or later (GPLv3+)
Requires-Python: >=3.8
License-File: LICENSE
Requires-Dist: deltabot-cli <7.0,>=6.2.0
Requires-Dist: pdfkit
Provides-Extra: dev
Requires-Dist: black ; extra == 'dev'
Requires-Dist: mypy ; extra == 'dev'
Requires-Dist: isort ; extra == 'dev'
Requires-Dist: pylint ; extra == 'dev'
Requires-Dist: pylama ; extra == 'dev'
Requires-Dist: pytest ; extra == 'dev'
Requires-Dist: types-requests ; extra == 'dev'
